{
    "meta": {
        "__export_time": 1659692294128,
        "__export_app": "firecamp_v2.6.1 ",
        "__export_version": 1
    },
    "project": {
        "name": "My collection",
        "description": "",
        "auth": {},
        "scripts": {
            "pre": "",
            "post": "",
            "test": ""
        },
        "meta": {
            "active_auth": "no_auth"
        }
    },
    "modules": [],
    "requests": [
        {
            "meta": {
                "name": "Chat App Socket IO",
                "description": "",
                "type": "socketio",
                "version": "2.0"
            },
            "url": {
                "slashes": false,
                "protocol": "",
                "hash": "",
                "pathname": "{{base}}",
                "auth": "",
                "host": "",
                "port": "",
                "hostname": "",
                "password": "",
                "username": "",
                "origin": "null",
                "href": "{{base}}",
                "path_params": [],
                "query_params": []
            },
            "config": {
                "version": "v3",
                "rejectUnauthorized": false,
                "timeout": 20000,
                "reconnection": false,
                "reconnectionAttempts": 3,
                "reconnectionDelay": 1000,
                "reconnectionDelayMax": 5000,
                "on_connect_listeners": []
            },
            "connections": [
                {
                    "name": "Default",
                    "forceNew": false,
                    "namespace": "",
                    "path": "",
                    "ping": false,
                    "ping_interval": 3000,
                    "transports": {
                        "websocket": true,
                        "polling": true
                    },
                    "headers": [
                        {
                            "key": "authorization",
                            "value": "Bearer eyJhbGciOiJIUzUxMiIsInR5cCI6IkpXVCJ9.eyJkYXRhIjoicXVhbmduZC5udGFAZ21haWwuY29tIiwiaWF0IjoxNjU5NTk3ODM1LCJleHAiOjE2OTExMzM4MzV9.ZaywQUf5i5DFMCuVYJsw24X5tqyOYPwT_UPaBucHfsRTdKo-ynUKdczBzSKR20tgD3onBDaG3o2aoTRPP44VBw",
                            "disable": false,
                            "type": "text"
                        }
                    ],
                    "query_params": [],
                    "auth": [],
                    "is_default": true
                }
            ],
            "listeners": [
                "createConversation",
                "leaveRoom",
                "message"
            ],
            "emitter_collection": [
                {
                    "name": "createConversation",
                    "body": [
                        {
                            "meta": {
                                "type": "json",
                                "envelope": ""
                            },
                            "payload": "{\n  \"uid\" : \"uid-41f6829c-0f0f-11ed-903b-c6ef0857e0cf\"\n}",
                            "path": ""
                        }
                    ],
                    "meta": {
                        "label": "createConversation",
                        "interval": "",
                        "ack": false
                    }
                },
                {
                    "name": "message",
                    "body": [
                        {
                            "meta": {
                                "type": "json",
                                "envelope": ""
                            },
                            "payload": "{\n  \"conversationId\": 46,\n  \"message\" : \"aaaaa\"\n}"
                        }
                    ],
                    "meta": {
                        "label": "sendMessage",
                        "interval": "",
                        "ack": false
                    }
                },
                {
                    "name": "leaveRoom",
                    "body": [
                        {
                            "meta": {
                                "type": "json",
                                "envelope": ""
                            },
                            "payload": "{\n  \"conversationId\": 46\n}"
                        }
                    ],
                    "meta": {
                        "label": "leaveRoom",
                        "interval": "",
                        "ack": false
                    }
                }
            ]
        }
    ],
    "environments": [
        {
            "name": "Production",
            "variables": {
                "variable_name": "variable_value"
            }
        },
        {
            "name": "Development",
            "variables": {
                "variable_name": "variable_value"
            }
        }
    ]
}